pipelm/__init__.py
pipelm/chat.py
pipelm/cli.py
pipelm/client.py
pipelm/downloader.py
pipelm/server.py
pipelm/utils.py
pipelm-0.1.2.dist-info/licenses/LICENSE
pipelm-0.1.2.dist-info/METADATA
pipelm-0.1.2.dist-info/WHEEL
pipelm-0.1.2.dist-info/entry_points.txt
pipelm-0.1.2.dist-info/top_level.txt
pipelm-0.1.2.dist-info/RECORD
