Metadata-Version: 2.4
Name: pipelm
Version: 0.1.2
Summary: A lightweight API server and CLI for running LLM models
Home-page: https://github.com/kashyaprparmar/pipelm
Author: Kashyap Parmar
Author-email: kashyaprparmar@gmail.com
Classifier: Development Status :: 3 - Alpha
Classifier: Intended Audience :: Developers
Classifier: License :: OSI Approved :: MIT License
Classifier: Programming Language :: Python :: 3
Classifier: Programming Language :: Python :: 3.8
Classifier: Programming Language :: Python :: 3.9
Classifier: Programming Language :: Python :: 3.10
Requires-Python: >=3.8
License-File: LICENSE
Requires-Dist: torch>=2.0.0
Requires-Dist: transformers>=4.30.0
Requires-Dist: huggingface-hub>=0.16.0
Requires-Dist: pydantic>=1.10.0
Requires-Dist: fastapi>=0.95.0
Requires-Dist: uvicorn>=0.22.0
Requires-Dist: requests>=2.28.0
Requires-Dist: rich>=12.0.0
Requires-Dist: appdirs>=1.4.4
Requires-Dist: python-dotenv>=1.0.0
Requires-Dist: accelerate>=0.20.0
Requires-Dist: sentencepiece>=0.1.99
Requires-Dist: bitsandbytes>=0.40.0
Requires-Dist: pillow>=11.2.1
Requires-Dist: pyfiglet>=1.0.2
Dynamic: author
Dynamic: author-email
Dynamic: classifier
Dynamic: description
Dynamic: description-content-type
Dynamic: home-page
Dynamic: license-file
Dynamic: requires-dist
Dynamic: requires-python
Dynamic: summary
